CHANGES.txt
COPYING
HACKING.txt
MANIFEST.in
README.txt
fc-qemu.conf
pyproject.toml
requirements.txt
setup.py
src/fc/__init__.py
src/fc.qemu.egg-info/PKG-INFO
src/fc.qemu.egg-info/SOURCES.txt
src/fc.qemu.egg-info/dependency_links.txt
src/fc.qemu.egg-info/entry_points.txt
src/fc.qemu.egg-info/namespace_packages.txt
src/fc.qemu.egg-info/not-zip-safe
src/fc.qemu.egg-info/requires.txt
src/fc.qemu.egg-info/top_level.txt
src/fc/qemu/__init__.py
src/fc/qemu/agent.py
src/fc/qemu/conftest.py
src/fc/qemu/default.conf
src/fc/qemu/directory.py
src/fc/qemu/ellipsis.py
src/fc/qemu/exc.py
src/fc/qemu/incoming.py
src/fc/qemu/logging.py
src/fc/qemu/main.py
src/fc/qemu/outgoing.py
src/fc/qemu/qemu.vm.cfg.in
src/fc/qemu/sysconfig.py
src/fc/qemu/timeout.py
src/fc/qemu/util.py
src/fc/qemu/hazmat/__init__.py
src/fc/qemu/hazmat/ceph.py
src/fc/qemu/hazmat/conftest.py
src/fc/qemu/hazmat/cpuscan.py
src/fc/qemu/hazmat/guestagent.py
src/fc/qemu/hazmat/qemu.py
src/fc/qemu/hazmat/qmp.py
src/fc/qemu/hazmat/supervise.py
src/fc/qemu/hazmat/volume.py
src/fc/qemu/hazmat/tests/__init__.py
src/fc/qemu/hazmat/tests/guestagent_test.py
src/fc/qemu/hazmat/tests/test_ceph.py
src/fc/qemu/hazmat/tests/test_cpuscan.py
src/fc/qemu/hazmat/tests/test_qemu.py
src/fc/qemu/hazmat/tests/test_volume.py
src/fc/qemu/tests/__init__.py
src/fc/qemu/tests/agent_test.py
src/fc/qemu/tests/incoming_test.py
src/fc/qemu/tests/outgoing_test.py
src/fc/qemu/tests/qemu_test.py
src/fc/qemu/tests/test_consul.py
src/fc/qemu/tests/test_logging.py
src/fc/qemu/tests/test_migration.py
src/fc/qemu/tests/test_timeout.py
src/fc/qemu/tests/vm_test.py
src/fc/qemu/tests/fixtures/simplevm.yaml