Metadata-Version: 2.1
Name: fc.qemu
Version: 1.4.0
Summary: Qemu VM management utilities
Home-page: http://github.com/flyingcircusio/fc.qemu
Author: Christian Kauhaus, Christian Theune
Author-email: mail@flyingcircus.io
License: BSD
Classifier: Development Status :: 5 - Production/Stable
Classifier: Environment :: Console
Classifier: Programming Language :: Python :: 3.8
License-File: COPYING
